moonbunny/__init__.py
moonbunny-0.1.0.dist-info/METADATA
moonbunny-0.1.0.dist-info/WHEEL
moonbunny-0.1.0.dist-info/RECORD
